Bastos.py
Bastos-0.1.dist-info/METADATA
Bastos-0.1.dist-info/WHEEL
Bastos-0.1.dist-info/top_level.txt
Bastos-0.1.dist-info/RECORD
