Metadata-Version: 2.1
Name: Bastos
Version: 0.1
Summary: A simple library to Bastosize the world
Home-page: UNKNOWN
Author: Hamza Khan
Author-email: hamzamania@gmail.com
License: UNKNOWN
Platform: UNKNOWN
Classifier: Programming Language :: Python :: 3
Classifier: License :: OSI Approved :: MIT License
Classifier: Operating System :: OS Independent
Requires-Python: >=3.6
